sparrow/__init__.py
sparrow/cli.py
sparrow/src/__init__.py
sparrow/src/commands.py
sparrow/src/helper.py
sparrow/src/manager.py
sparrow/src/parser.py
sparrow_gtm_cli-3.0.0.dist-info/LICENCE
sparrow_gtm_cli-3.0.0.dist-info/METADATA
sparrow_gtm_cli-3.0.0.dist-info/WHEEL
sparrow_gtm_cli-3.0.0.dist-info/entry_points.txt
sparrow_gtm_cli-3.0.0.dist-info/top_level.txt
sparrow_gtm_cli-3.0.0.dist-info/RECORD
