Metadata-Version: 2.1
Name: sparrow-gtm-cli
Version: 3.0.0
Summary: Google GTM Wrapper
Home-page: UNKNOWN
Author: Fady F Salem
Author-email: ffaried@talabat.com
License: GPLv3
Download-URL: https://github.com/fadyfaried/sparrow-gtm-cli
Keywords: gtm,sparrow-cli
Platform: UNKNOWN
Classifier: Development Status :: 5 - Production/Stable
Classifier: Intended Audience :: Developers
Classifier: Intended Audience :: Information Technology
Classifier: Intended Audience :: System Administrators
Classifier: Programming Language :: Python :: 2
Classifier: Programming Language :: Python :: 2.7
Classifier: Programming Language :: Python :: 3
Classifier: Programming Language :: Python :: 3.5
Classifier: Programming Language :: Python :: 3.6
Classifier: Programming Language :: Python :: 3.7
Classifier: Natural Language :: English
